wigle_csv/__init__.py
wigle_csv/classes.py
wigle_csv/py.typed
wigle_csv/reader.py
wigle_csv-1.0.0.dist-info/LICENSE
wigle_csv-1.0.0.dist-info/WHEEL
wigle_csv-1.0.0.dist-info/METADATA
wigle_csv-1.0.0.dist-info/RECORD
