Metadata-Version: 2.1
Name: wigle-csv
Version: 1.0.0
Summary: WiGLE CSV format parser
Home-page: https://github.com/jyooru/wigle-csv
License: MIT
Keywords: WiGLE,wifi,csv
Author: Joel
Author-email: joel@joel.tokyo
Requires-Python: >=3.7,<4.0
Classifier: Development Status :: 5 - Production/Stable
Classifier: Intended Audience :: Developers
Classifier: License :: OSI Approved :: MIT License
Classifier: Operating System :: OS Independent
Classifier: Programming Language :: Python
Classifier: Programming Language :: Python :: 3
Classifier: Programming Language :: Python :: 3 :: Only
Classifier: Programming Language :: Python :: 3.10
Classifier: Programming Language :: Python :: 3.7
Classifier: Programming Language :: Python :: 3.8
Classifier: Programming Language :: Python :: 3.9
Classifier: Topic :: Software Development :: Libraries :: Python Modules
Classifier: Typing :: Typed
Requires-Dist: dataclass-csv (>=1.4.0,<2.0.0)
Project-URL: Repository, https://github.com/jyooru/wigle-csv
